battery_bot_telegram/__init__.py
battery_bot_telegram-0.1.3.dist-info/entry_points.txt
battery_bot_telegram-0.1.3.dist-info/WHEEL
battery_bot_telegram-0.1.3.dist-info/METADATA
battery_bot_telegram-0.1.3.dist-info/RECORD
